optimates/__init__.py
optimates/combinatorics.py
optimates/py.typed
optimates/search.py
optimates/utils.py
optimates-0.1.0.dist-info/METADATA
optimates-0.1.0.dist-info/WHEEL
optimates-0.1.0.dist-info/RECORD
